bfjira/__init__.py
bfjira/git_utils.py
bfjira/jira_utils.py
bfjira/log_config.py
bfjira/main.py
bfjira-0.7.3.dist-info/LICENSE
bfjira-0.7.3.dist-info/METADATA
bfjira-0.7.3.dist-info/WHEEL
bfjira-0.7.3.dist-info/entry_points.txt
bfjira-0.7.3.dist-info/RECORD
