Metadata-Version: 2.3
Name: bfjira
Version: 0.7.3
Summary: Create Git branches from Jira tickets
License: MIT
Keywords: jira,git,workflow,automation
Author: Nick Hobart
Author-email: nick@hobart.io
Requires-Python: >=3.10,<4.0
Classifier: Development Status :: 4 - Beta
Classifier: Intended Audience :: Developers
Classifier: License :: OSI Approved :: MIT License
Classifier: Programming Language :: Python :: 3
Classifier: Programming Language :: Python :: 3.10
Classifier: Programming Language :: Python :: 3.11
Classifier: Programming Language :: Python :: 3.12
Classifier: Programming Language :: Python :: 3.13
Requires-Dist: colorlog (>=6.7.0,<7.0.0)
Requires-Dist: gitpython (>=3.1.37,<4.0.0)
Requires-Dist: jira (>=3.5.1,<4.0.0)
Requires-Dist: pyyaml (>=6.0.1,<7.0.0)
Requires-Dist: requests (>=2.31.0,<2.33.0)
Project-URL: Documentation, https://github.com/nickhobart/bfjira#readme
Project-URL: Repository, https://github.com/nickhobart/bfjira
